{"assets":{"37269840B37BC74238D37ED6326D39DC":{"type":"texture","index":0,"assetRequest":{"type":"slide","state":"contents","slide":"none"},"url":{"native":"assets/17240CAD-7938-42BE-8C4A-00AC12363F73.pdf"},"width":1920,"height":1080},"385168809F22B475A4C9F17C9886FF7C":{"type":"texture","index":1,"assetRequest":{"type":"slide","state":"contents","slide":"none"},"url":{"native":"assets/17240CAD-7938-42BE-8C4A-00AC12363F73.pdf"},"width":1920,"height":1080}},"events":[{"effects":[{"beginTime":0,"baseLayer":{"animations":[],"initialState":{"affineTransform":[1,0,0,1,0,0],"masksToBounds":false,"rotation":0,"scale":1,"position":{"pointX":960,"pointY":540},"width":1920,"sublayerTransform":[1,0,0,0,0,1,0,0,0,0,1,0,0,0,0,1],"contentsRect":{"y":0,"x":0,"width":1,"height":1},"opacity":1,"edgeAntialiasingMask":251658240,"height":1080,"hidden":false,"anchorPoint":{"pointX":0.5,"pointY":0.5}},"objectID":"0","layers":[{"animations":[],"initialState":{"affineTransform":[1,0,0,1,0,0],"masksToBounds":false,"rotation":0,"scale":1,"position":{"pointX":960,"pointY":540},"width":1920,"sublayerTransform":[1,0,0,0,0,1,0,0,0,0,1,-0.0003500791246677598,0,0,0,1],"contentsRect":{"y":0,"x":0,"width":1,"height":1},"opacity":1,"edgeAntialiasingMask":251658240,"height":1080,"hidden":false,"anchorPoint":{"pointX":0.5,"pointY":0.5}},"layers":[{"animations":[],"layers":[],"texturedRectangle":{"isBackgroundTexture":false,"singleTextureOpacity":1,"textureType":0,"textBaseline":0,"textXHeight":0,"isVerticalText":false},"initialState":{"affineTransform":[1,0,0,1,0,0],"masksToBounds":false,"rotation":0,"scale":1,"position":{"pointX":960,"pointY":540},"width":1920,"sublayerTransform":[1,0,0,0,0,1,0,0,0,0,1,0,0,0,0,1],"contentsRect":{"y":0,"x":0,"width":1,"height":1},"opacity":1,"edgeAntialiasingMask":0,"height":1080,"hidden":false,"anchorPoint":{"pointX":0.5,"pointY":0.5}},"texture":"385168809F22B475A4C9F17C9886FF7C"},{"animations":[{"timeOffset":0,"from":{"scalar":false},"beginTime":0,"repeatCount":0,"fillMode":"both","property":"hidden","autoreverses":false,"duration":0.01,"to":{"scalar":true}}],"layers":[],"texturedRectangle":{"isBackgroundTexture":false,"singleTextureOpacity":1,"textureType":0,"textBaseline":0,"textXHeight":0,"isVerticalText":false},"initialState":{"affineTransform":[1,0,0,1,0,0],"masksToBounds":false,"rotation":0,"scale":1,"position":{"pointX":960,"pointY":540},"width":1920,"sublayerTransform":[1,0,0,0,0,1,0,0,0,0,1,0,0,0,0,1],"contentsRect":{"y":0,"x":0,"width":1,"height":1},"opacity":1,"edgeAntialiasingMask":0,"height":1080,"hidden":false,"anchorPoint":{"pointX":0.5,"pointY":0.5}},"texture":"37269840B37BC74238D37ED6326D39DC"}]}]},"effects":[],"duration":0.01,"type":"transition","name":"none","objectID":"0"}],"automaticPlay":false,"hyperlinks":[],"accessibility":[{"text":"Approaches","targetRectangle":{"y":588.394775390625,"x":1521.002440214157,"width":190.29,"height":36}},{"text":"User Flows","targetRectangle":{"y":624.394775390625,"x":1521.002440214157,"width":172.5900000000001,"height":36}},{"text":"Define","targetRectangle":{"y":27.49168360233307,"x":1490.169189453125,"width":173.95,"height":60}},{"text":"Design QA","targetRectangle":{"y":974.6446529626846,"x":1478.60498046875,"width":286,"height":60}},{"text":"Ideate","targetRectangle":{"y":519.5518184900284,"x":1484.532470703125,"width":169.5999999999999,"height":60}},{"text":"User Test","targetRectangle":{"y":887.5253902673721,"x":1482.747436523438,"width":245.1500000000001,"height":60}},{"text":"Problem Statement","targetRectangle":{"y":96.40213012695312,"x":1526.16418337822,"width":305.4299999999998,"height":36}},{"text":"User Research","targetRectangle":{"y":132.4021301269531,"x":1526.16418337822,"width":228.8099999999999,"height":36}},{"text":"Interview","targetRectangle":{"y":168.4021301269531,"x":1576.16418337822,"width":149.6700000000001,"height":36}},{"text":"Survey","targetRectangle":{"y":204.4021301269531,"x":1576.16418337822,"width":108.5999999999999,"height":36}},{"text":"Contextual Inquiry","targetRectangle":{"y":240.4021301269531,"x":1576.16418337822,"width":296.6700000000001,"height":36}},{"text":"Persona","targetRectangle":{"y":276.4021301269531,"x":1576.16418337822,"width":128.6700000000001,"height":36}},{"text":"Heuristic Evaluation","targetRectangle":{"y":412.5165710449219,"x":1521.002440214157,"width":313.6199999999999,"height":36}},{"text":"Comparative Analysis","targetRectangle":{"y":448.5165710449219,"x":1521.002440214157,"width":340.77,"height":36}},{"text":"https://confluence.roblox.com/display/DESIGN/Studio+User+Research","targetRectangle":{"y":991.9396419081056,"x":138.2819506585444,"width":1108.739999999999,"height":36}},{"text":"Wireframes","targetRectangle":{"y":755.49755859375,"x":1523.374998807907,"width":180.96,"height":36}},{"text":"Hi-fi Prototypes","targetRectangle":{"y":791.49755859375,"x":1523.374998807907,"width":249.51,"height":36}},{"text":"Interactive Prototypes","targetRectangle":{"y":827.49755859375,"x":1523.374998807907,"width":350.6700000000001,"height":36}},{"text":"Analyze","targetRectangle":{"y":343.6061092615128,"x":1485.007446289062,"width":213.7,"height":60}},{"text":"pasted-image.png","targetRectangle":{"y":103.6046204721259,"x":26.01497350815438,"width":1412.090942382812,"height":818.2366943359372}},{"text":"Prototype","targetRectangle":{"y":686.5870968103409,"x":1487.380004882812,"width":268.45,"height":60}}],"baseLayer":{"animations":[],"initialState":{"affineTransform":[1,0,0,1,0,0],"masksToBounds":false,"rotation":0,"scale":1,"position":{"pointX":960,"pointY":540},"width":1920,"sublayerTransform":[1,0,0,0,0,1,0,0,0,0,1,0,0,0,0,1],"contentsRect":{"y":0,"x":0,"width":1,"height":1},"opacity":1,"edgeAntialiasingMask":251658240,"height":1080,"hidden":false,"anchorPoint":{"pointX":0.5,"pointY":0.5}},"objectID":"0","layers":[{"animations":[],"initialState":{"affineTransform":[1,0,0,1,0,0],"masksToBounds":false,"rotation":0,"scale":1,"position":{"pointX":960,"pointY":540},"width":1920,"sublayerTransform":[1,0,0,0,0,1,0,0,0,0,1,-0.0003500791246677598,0,0,0,1],"contentsRect":{"y":0,"x":0,"width":1,"height":1},"opacity":1,"edgeAntialiasingMask":251658240,"height":1080,"hidden":false,"anchorPoint":{"pointX":0.5,"pointY":0.5}},"layers":[{"animations":[],"layers":[],"texturedRectangle":{"isBackgroundTexture":false,"singleTextureOpacity":1,"textureType":0,"textBaseline":0,"textXHeight":0,"isVerticalText":false},"initialState":{"affineTransform":[1,0,0,1,0,0],"masksToBounds":false,"rotation":0,"scale":1,"position":{"pointX":960,"pointY":540},"width":1920,"sublayerTransform":[1,0,0,0,0,1,0,0,0,0,1,0,0,0,0,1],"contentsRect":{"y":0,"x":0,"width":1,"height":1},"opacity":1,"edgeAntialiasingMask":0,"height":1080,"hidden":false,"anchorPoint":{"pointX":0.5,"pointY":0.5}},"texture":"37269840B37BC74238D37ED6326D39DC"}]}]}}]}